kahi_minciencias_opendata_projects/Kahi_minciencias_opendata_projects.py
kahi_minciencias_opendata_projects/__init__.py
kahi_minciencias_opendata_projects/_version.py
kahi_minciencias_opendata_projects/parser.py
kahi_minciencias_opendata_projects/process_one.py
Kahi_minciencias_opendata_projects-0.1.0b0.dist-info/METADATA
Kahi_minciencias_opendata_projects-0.1.0b0.dist-info/WHEEL
Kahi_minciencias_opendata_projects-0.1.0b0.dist-info/top_level.txt
Kahi_minciencias_opendata_projects-0.1.0b0.dist-info/RECORD
