Metadata-Version: 2.2
Name: Kahi_minciencias_opendata_projects
Version: 0.1.0b0
Summary: Kahi plugin minciencias_opendata_projects
Home-page: https://github.com/colav/Kahi_plugins
Author: Colav
Author-email: colav@udea.edu.co
License: BSD
Requires-Dist: kahi
Requires-Dist: pymongo
Dynamic: author
Dynamic: author-email
Dynamic: description
Dynamic: description-content-type
Dynamic: home-page
Dynamic: license
Dynamic: requires-dist
Dynamic: summary
